ltx_video/__init__.py
ltx_video/inference.py
ltx_video/models/__init__.py
ltx_video/models/autoencoders/__init__.py
ltx_video/models/autoencoders/causal_conv3d.py
ltx_video/models/autoencoders/causal_video_autoencoder.py
ltx_video/models/autoencoders/conv_nd_factory.py
ltx_video/models/autoencoders/dual_conv3d.py
ltx_video/models/autoencoders/latent_upsampler.py
ltx_video/models/autoencoders/pixel_norm.py
ltx_video/models/autoencoders/pixel_shuffle.py
ltx_video/models/autoencoders/vae.py
ltx_video/models/autoencoders/vae_encode.py
ltx_video/models/autoencoders/video_autoencoder.py
ltx_video/models/transformers/__init__.py
ltx_video/models/transformers/attention.py
ltx_video/models/transformers/embeddings.py
ltx_video/models/transformers/symmetric_patchifier.py
ltx_video/models/transformers/transformer3d.py
ltx_video/pipelines/__init__.py
ltx_video/pipelines/crf_compressor.py
ltx_video/pipelines/pipeline_ltx_video.py
ltx_video/schedulers/__init__.py
ltx_video/schedulers/rf.py
ltx_video/utils/__init__.py
ltx_video/utils/diffusers_config_mapping.py
ltx_video/utils/prompt_enhance_utils.py
ltx_video/utils/skip_layer_strategy.py
ltx_video/utils/torch_utils.py
ltx_video-0.1.2.dist-info/licenses/LICENSE
ltx_video-0.1.2.dist-info/METADATA
ltx_video-0.1.2.dist-info/WHEEL
ltx_video-0.1.2.dist-info/top_level.txt
ltx_video-0.1.2.dist-info/RECORD
