Metadata-Version: 2.4
Name: ltx-video
Version: 0.1.2
Summary: A package for LTX-Video model
Author-email: LTX-Video Team <ltx-video@lightricks.com>
Classifier: Programming Language :: Python :: 3
Classifier: Operating System :: OS Independent
Requires-Python: >=3.10
License-File: LICENSE
Requires-Dist: torch>=2.1.0
Requires-Dist: diffusers>=0.28.2
Requires-Dist: transformers<4.52.0,>=4.47.2
Requires-Dist: sentencepiece>=0.1.96
Requires-Dist: huggingface-hub~=0.30
Requires-Dist: einops
Requires-Dist: timm
Provides-Extra: inference
Requires-Dist: imageio[ffmpeg]; extra == "inference"
Requires-Dist: av; extra == "inference"
Requires-Dist: torchvision; extra == "inference"
Provides-Extra: test
Requires-Dist: pytest; extra == "test"
Dynamic: license-file
